libtalley/__init__.py
libtalley/__version__
libtalley/aisc-shapes-database-v15-0-SI.csv.bz2
libtalley/aisc-shapes-database-v15-0-US.csv.bz2
libtalley/color.py
libtalley/colors.json
libtalley/ipython.py
libtalley/latex.py
libtalley/matplotlib.py
libtalley/mutt.py
libtalley/sap2000.py
libtalley/shapes-resources.json
libtalley/steel-materials-us.csv
libtalley/steeldesign.py
libtalley/text.py
libtalley/units.py
libtalley/utils.py
libtalley-5.0.0.dist-info/METADATA
libtalley-5.0.0.dist-info/WHEEL
libtalley-5.0.0.dist-info/top_level.txt
libtalley-5.0.0.dist-info/RECORD
