Metadata-Version: 2.1
Name: libtalley
Version: 5.0.0
Summary: A collection of helpful functions and doodads.
Home-page: https://github.com/otaithleigh/libtalley-py
Author: Peter Talley
Author-email: peterctalley@gmail.com
License: MIT
Requires-Python: >=3.8
Requires-Dist: numpy >=1.15.0
Requires-Dist: pandas
Requires-Dist: tabulate
Requires-Dist: unyt >=2.8
